chemical_kinetics/__init__.py
chemical_kinetics/data.py
chemical_kinetics/fit.py
chemical_kinetics/plot.py
chemical_kinetics-1.0.5.dist-info/LICENSE
chemical_kinetics-1.0.5.dist-info/METADATA
chemical_kinetics-1.0.5.dist-info/WHEEL
chemical_kinetics-1.0.5.dist-info/top_level.txt
chemical_kinetics-1.0.5.dist-info/RECORD
