Metadata-Version: 2.1
Name: chemical-kinetics
Version: 1.0.5
Summary: Module to fit data with a chemical kinetics model.
Home-page: https://github.com/flboudoire/chemical-kinetics
Author: Florent Boudoire
Author-email: flboudoire@gmail.com
License: UNKNOWN
Platform: UNKNOWN
Classifier: Programming Language :: Python :: 3
Classifier: License :: OSI Approved :: MIT License
Classifier: Operating System :: OS Independent
Requires-Python: >=3.6
